RasPyDHT-1.0.0.dist-info/DESCRIPTION.rst
RasPyDHT-1.0.0.dist-info/METADATA
RasPyDHT-1.0.0.dist-info/RECORD
RasPyDHT-1.0.0.dist-info/WHEEL
RasPyDHT-1.0.0.dist-info/entry_points.txt
RasPyDHT-1.0.0.dist-info/metadata.json
RasPyDHT-1.0.0.dist-info/top_level.txt
raspydht/DHT_lcd1602.py
raspydht/DHT_read.py
raspydht/LCD1602.py
raspydht/__init__.py
raspydht/__main__.py
raspydhtplot/DHT_plot_rt.py
raspydhtplot/DataSet.py
raspydhtplot/__init__.py
raspydhtplot/__main__.py
rtplot/DHT_plot_rt.py
rtplot/DataSet.py
rtplot/__init__.py
